{
  "About": "About",
  "News": "News",
  "Contact Us": "Contact Us",
  "Services": "Services",
  "#1 Car": "#1 Car",
  "Your": "Your",
  "Servicing App": "Servicing App",
  "Get The App": "Get The App",
  "Download Now": "Download Now",
  "Download on the": "Download on the",
  "Why Choose us": "Why Choose us",
  "We are an": "We are an",
  "Egyptian": "Egyptian",
  "company": "company",
  "that was born out of the Need to find easy": "that was born out of the Need to find easy",
  "Automechanic connects car owners in Cairo with mechanic services and workshops": "Automechanic connects car owners in Cairo with mechanic services and workshops",
  "in their locality, with a list of prices and services, and locations available at the touch of a button": "in their locality, with a list of prices and services, and locations available at the touch of a button",
  "Easy & Friendly": "Easy & Friendly",
  "The app was perfectly designed and developed based on an extensive research": "The app was perfectly designed and developed based on an extensive research",
  "Tranceprancy": "Tranceprancy",
  "Transparent listing of Quality, Prices and Service delivery time": "Transparent listing of Quality, Prices and Service delivery time",
  "Customer Support": "Customer Support",
  "We are always available to guide and support you at anytime": "We are always available to guide and support you at anytime",
  "join As A Workshop": "join As A Workshop",
  "We bring a wealth of": "We bring a wealth of",
  "Experience": "Experience",
  "from": "from",
  "a wide rang of backgrounds": "a wide rang of backgrounds",
  "in their locality, with a list of prices and services, and locations available at the touch of a button.": "in their locality, with a list of prices and services, and locations available at the touch of a button.",
  "Workshop name": "Workshop name",
  "workshop field": "workshop field",
  "Qualified workshops": "Qualified workshops",
  "Cities": "Cities",
  "Car Wash centers": "Car Wash centers",
  "Our Services": "Our Services",
  "Mechanic": "Mechanic",
  "Electrical": "Electrical",
  "Wheel Align": "Wheel Align",
  "Car Wash": "Car Wash",
  "General Repair": "General Repair",
  "Oil Change": "Oil Change",
  "Diagnosis & reporting": "Diagnosis & reporting",
  "Suspension": "Suspension",
  "Submit": "Submit",
  "Full Name": "Full Name",
  "Phone Number": "Phone Number",
  "Email": "Email",
  "Company": "Company",
  "Message": "Message",
  "about": "About",
  "Contact Information": "Contact Information",
  "Get in touch with us": "Get in touch with us",
  "We know that sometimes a personal conversation is the best solution. If you need immediate support or have specific questions, don't hesitate to call or email us. Our dedicated team is available to discuss your concerns and help you further.": "We know that sometimes a personal conversation is the best solution. If you need immediate support or have specific questions, don't hesitate to call or email us. Our dedicated team is available to discuss your concerns and help you further.",
  "Batteries Workshops & Tires": "Batteries Workshops & Tires",
  "get the app now and join us as a workshop": "get the app now and join us as a workshop"
}
